adafruit_circuitpython_fancyled-1.4.24.dist-info/licenses/LICENSE
adafruit_fancyled/__init__.py
adafruit_fancyled/adafruit_fancyled.py
adafruit_fancyled/fastled_helpers.py
adafruit_circuitpython_fancyled-1.4.24.dist-info/METADATA
adafruit_circuitpython_fancyled-1.4.24.dist-info/WHEEL
adafruit_circuitpython_fancyled-1.4.24.dist-info/top_level.txt
adafruit_circuitpython_fancyled-1.4.24.dist-info/RECORD
