Metadata-Version: 2.4
Name: adafruit-circuitpython-fancyled
Version: 1.4.24
Summary: CircuitPython FancyLED helper library for LED animations.
Author-email: Adafruit Industries <circuitpython@adafruit.com>
License: MIT
Project-URL: Homepage, https://github.com/adafruit/Adafruit_CircuitPython_FancyLED
Keywords: adafruit,fancyled,fastled,led,animation,rgb,hardware,micropython,circuitpython
Classifier: Intended Audience :: Developers
Classifier: Topic :: Software Development :: Libraries
Classifier: Topic :: Software Development :: Embedded Systems
Classifier: Topic :: System :: Hardware
Classifier: License :: OSI Approved :: MIT License
Classifier: Programming Language :: Python :: 3
License-File: LICENSE
Provides-Extra: optional
Dynamic: license-file
